migration_db/__init__.py
migration_db/common_utils/__init__.py
migration_db/common_utils/calc_time.py
migration_db/common_utils/compare_two_dict.py
migration_db/common_utils/constant.py
migration_db/common_utils/context.py
migration_db/common_utils/database.py
migration_db/common_utils/file.py
migration_db/common_utils/format_time.py
migration_db/common_utils/handle_git.py
migration_db/common_utils/handle_remove_read_only.py
migration_db/common_utils/handle_str.py
migration_db/common_utils/lib.py
migration_db/common_utils/log.py
migration_db/common_utils/my_db.py
migration_db/common_utils/path.py
migration_db/common_utils/read_file.py
migration_db/common_utils/requirements.txt
migration_db/common_utils/template_parse.py
migration_db/common_utils/write_file.py
migration_db/common_utils/conf/config.py
migration_db/common_utils/conf/constant.py
migration_db/common_utils/conf/data_source_route.py
migration_db/common_utils/conf/study_info_route.py
migration_db/common_utils/dto/base_dto.py
migration_db/common_utils/s3/s3.py
migration_db/migration/__init__.py
migration_db/migration/requirements.txt
migration_db/migration/core/__init__.py
migration_db/migration/core/_migration.py
migration_db/migration/core/backup.py
migration_db/migration/core/base.py
migration_db/migration/core/build_test_platform_data.py
migration_db/migration/core/build_update_sql.py
migration_db/migration/core/execute_script.py
migration_db/migration/core/handle_external_condition_mapping_data.py
migration_db/migration/core/handle_file.py
migration_db/migration/core/handle_procedures.py
migration_db/migration/core/handle_special_field.py
migration_db/migration/core/handle_sql_statement.py
migration_db/migration/core/handle_table_action.py
migration_db/migration/core/incremental_sql.py
migration_db/migration/core/match_ids.py
migration_db/migration/core/migration_db_from_s3.py
migration_db/migration/core/redis_biz.py
migration_db/migration/core/refresh_incremental_sql.py
migration_db-1.0.75.dist-info/LICENSE
migration_db-1.0.75.dist-info/METADATA
migration_db-1.0.75.dist-info/WHEEL
migration_db-1.0.75.dist-info/top_level.txt
migration_db-1.0.75.dist-info/RECORD
