Metadata-Version: 2.1
Name: migration-db
Version: 1.0.75
Summary: Migrate database files
Home-page: http://example.com
Author: xiaodong.li
Author-email: 
License: UNKNOWN
Platform: UNKNOWN
Classifier: Programming Language :: Python :: 3.9
License-File: LICENSE
Requires-Dist: lxml (>=4.8.0)
Requires-Dist: redis (>=4.3.1)
Requires-Dist: jinja2 (>=3.1.2)
Requires-Dist: mysql-connector-python (>=8.3.0)
Requires-Dist: slicing (>=1.0.6)
Requires-Dist: GitPython (>=3.1.32)
Requires-Dist: werkzeug (>=3.0.1)
Requires-Dist: eclinical-requester (>=1.0.9)
